arsr/__init__.py
arsr/arsr.py
arsr/srmodels/__init__.py
arsr-2.0.2.dist-info/LICENSE
arsr-2.0.2.dist-info/METADATA
arsr-2.0.2.dist-info/WHEEL
arsr-2.0.2.dist-info/top_level.txt
arsr-2.0.2.dist-info/RECORD
